odoo/addons/product_document_domain/README.rst
odoo/addons/product_document_domain/__init__.py
odoo/addons/product_document_domain/__manifest__.py
odoo/addons/product_document_domain/i18n/es.po
odoo/addons/product_document_domain/i18n/it.po
odoo/addons/product_document_domain/i18n/product_document_domain.pot
odoo/addons/product_document_domain/models/__init__.py
odoo/addons/product_document_domain/models/product_product.py
odoo/addons/product_document_domain/models/product_template.py
odoo/addons/product_document_domain/readme/CONTRIBUTORS.md
odoo/addons/product_document_domain/readme/DESCRIPTION.md
odoo/addons/product_document_domain/readme/USAGE.md
odoo/addons/product_document_domain/static/description/icon.png
odoo/addons/product_document_domain/static/description/icon.svg
odoo/addons/product_document_domain/static/description/index.html
odoo/addons/product_document_domain/tests/__init__.py
odoo/addons/product_document_domain/tests/test_product_document_domain.py
odoo/addons/product_document_domain/views/product_document_view.xml
odoo_addon_product_document_domain-17.0.1.0.0.5.dist-info/METADATA
odoo_addon_product_document_domain-17.0.1.0.0.5.dist-info/WHEEL
odoo_addon_product_document_domain-17.0.1.0.0.5.dist-info/top_level.txt
odoo_addon_product_document_domain-17.0.1.0.0.5.dist-info/RECORD
